tunneltop/Session.vim
tunneltop/tunneltop.py
tunneltop-0.4.6.dist-info/LICENSE
tunneltop-0.4.6.dist-info/METADATA
tunneltop-0.4.6.dist-info/WHEEL
tunneltop-0.4.6.dist-info/entry_points.txt
tunneltop-0.4.6.dist-info/RECORD
