Metadata-Version: 2.3
Name: tunneltop
Version: 0.4.6
Summary: A top-like tunnel manager
License: GPL-3.0
Keywords: tunnel,top,ssh
Author: terminaldweller
Author-email: devi@terminaldweller.com
Requires-Python: >=3.11,<4.0
Classifier: Environment :: Console
Classifier: License :: OSI Approved :: GNU General Public License v3 (GPLv3)
Classifier: Programming Language :: Python :: 3
Classifier: Programming Language :: Python :: 3.11
Classifier: Programming Language :: Python :: 3.12
Classifier: Programming Language :: Python :: 3.13
Project-URL: Homepage, https://github.com/terminaldweller/tunneltop
Project-URL: Repository, https://github.com/terminaldweller/tunneltop
